agent_sdk/__init__.py
agent_sdk/agent.py
agent_sdk/agent_context.py
agent_sdk/agent_sdk.py
agent_sdk/client.py
agent_sdk/hyperliquid.py
agent_sdk/memory.py
agent_sdk/platforms.py
agent_sdk/polymarket.py
agent_sdk/py.typed
agent_sdk/swidge.py
agent_sdk/types/__init__.py
agent_sdk/types/base.py
agent_sdk/types/common.py
agent_sdk/types/config.py
agent_sdk/types/hyperliquid.py
agent_sdk/types/jobs.py
agent_sdk/types/ledger.py
agent_sdk/types/logging.py
agent_sdk/types/memory.py
agent_sdk/types/messaging.py
agent_sdk/types/polymarket.py
agent_sdk/types/positions.py
agent_sdk/types/suggestions.py
agent_sdk/types/swidge.py
agent_sdk/types/transactions.py
agent_sdk/utils/__init__.py
circuit_agent_sdk-1.3.5.dist-info/METADATA
circuit_agent_sdk-1.3.5.dist-info/WHEEL
circuit_agent_sdk-1.3.5.dist-info/RECORD
