Metadata-Version: 2.4
Name: circuit-agent-sdk
Version: 1.3.5
Summary: Official Python SDK for building and deploying agents on the Circuit platform
Project-URL: Repository, https://github.com/circuitorg/agent-sdk-python
Project-URL: Issues, https://github.com/circuitorg/agent-sdk-python/issues
Author-email: Circuit <kyle@selvlabs.com>
License: Proprietary
Keywords: agent,circuit,sdk
Classifier: Development Status :: 3 - Alpha
Classifier: Intended Audience :: Developers
Classifier: License :: Other/Proprietary License
Classifier: Operating System :: OS Independent
Classifier: Programming Language :: Python :: 3
Classifier: Programming Language :: Python :: 3.12
Classifier: Programming Language :: Python :: 3.13
Requires-Python: >=3.12
Requires-Dist: fastapi==0.109.0
Requires-Dist: mangum==0.17.0
Requires-Dist: pydantic>=2.0.0
Requires-Dist: python-dotenv>=1.0.0
Requires-Dist: requests==2.31.0
Requires-Dist: solana>=0.30.0
Requires-Dist: solders>=0.18.0
Requires-Dist: toml==0.10.2
Requires-Dist: uvicorn==0.27.0
Requires-Dist: web3>=6.0.0
Provides-Extra: dev
Requires-Dist: mypy>=1.0.0; extra == 'dev'
Requires-Dist: pre-commit>=3.0.0; extra == 'dev'
Requires-Dist: pytest-asyncio>=0.21.0; extra == 'dev'
Requires-Dist: pytest>=7.0.0; extra == 'dev'
Requires-Dist: ruff>=0.1.0; extra == 'dev'
Provides-Extra: docs
Requires-Dist: mkdocs-material>=9.0.0; extra == 'docs'
Requires-Dist: mkdocs>=1.5.0; extra == 'docs'
Requires-Dist: mkdocstrings[python]>=0.23.0; extra == 'docs'
